minicheck/__init__.py
minicheck/check.py
minicheck-0.1.1.dist-info/licenses/LICENSE
minicheck-0.1.1.dist-info/METADATA
minicheck-0.1.1.dist-info/WHEEL
minicheck-0.1.1.dist-info/top_level.txt
minicheck-0.1.1.dist-info/RECORD
