Metadata-Version: 2.4
Name: minicheck
Version: 0.1.1
Summary: A minimal python testing tool that makes writing, organizing and executing tests fast and straightforward, keeping development workflows simple and clear.
Author: Christian Garcia
Author-email: 
License: MIT
Project-URL: Homepage, https://github.com/christiangarcia0311/minicheck-testing-tool
Keywords: testing,cli,web,flask,pytest-alternative
Requires-Python: >=3.8
License-File: LICENSE
Requires-Dist: colorama
Dynamic: license-file
Dynamic: requires-python
